LICENSE.txt
MANIFEST.in
README.md
setup.cfg
setup.py
slue_evaluator/__init__.py
slue_evaluator/eval.py
slue_evaluator/slue_toolkit_eval_utils.py
slue_evaluator/slue_toolkit_generic_utils.py
slue_evaluator.egg-info/PKG-INFO
slue_evaluator.egg-info/SOURCES.txt
slue_evaluator.egg-info/dependency_links.txt
slue_evaluator.egg-info/requires.txt
slue_evaluator.egg-info/top_level.txt
slue_evaluator/data/dev.combined.wrd
slue_evaluator/data/dev.raw.wrd
slue_evaluator/data/fine-tune.combined.wrd
slue_evaluator/data/fine-tune.raw.wrd