Metadata-Version: 2.1
Name: slue-evaluator
Version: 0.8
Summary: Evalutes the model's output on slue dataset
Home-page: https://github.com/RAGHUDINESH/slue_evaluator
Download-URL: https://github.com/RAGHUDINESH/slue_evaluator/archive/refs/tags/v_01.tar.gz
Author: RAGHU DINESH
Author-email: raghudinesh98@gmail.com
License: MIT
Keywords: E2E,EVALUATION,NER
Classifier: Development Status :: 3 - Alpha
Classifier: Intended Audience :: Developers
Classifier: Topic :: Software Development :: Build Tools
Classifier: License :: OSI Approved :: MIT License
Classifier: Programming Language :: Python :: 3
Classifier: Programming Language :: Python :: 3.4
Classifier: Programming Language :: Python :: 3.5
Classifier: Programming Language :: Python :: 3.6
Classifier: Programming Language :: Python :: 3.7
Classifier: Programming Language :: Python :: 3.8
Classifier: Programming Language :: Python :: 3.9
Classifier: Programming Language :: Python :: 3.10
License-File: LICENSE.txt
